{"errors":[],"warnings":[],"namedChunkGroups":{"polyfill":{"chunks":[2,0,12],"assets":["webpack-runtime-980e121073cb30c1f4e4.js","webpack-runtime-980e121073cb30c1f4e4.js.map","commons-2a628ef3c0ffddbbec42.js","commons-2a628ef3c0ffddbbec42.js.map","polyfill-8b52c04d9c14ad2efd64.js","polyfill-8b52c04d9c14ad2efd64.js.map"],"children":{},"childAssets":{}},"app":{"chunks":[2,11,13,3],"assets":["webpack-runtime-980e121073cb30c1f4e4.js","webpack-runtime-980e121073cb30c1f4e4.js.map","framework-85aff51d15c28c7fbe5f.js","framework-85aff51d15c28c7fbe5f.js.map","styles.b439bc9f915495c62296.css","styles-5379f07abcd59a0e64bf.js","styles-5379f07abcd59a0e64bf.js.map","app-596f89afb85ee861135b.js","app-596f89afb85ee861135b.js.map"],"children":{},"childAssets":{}},"component---src-pages-30-minute-jams-js":{"chunks":[1,0,5],"assets":["a9a7754c-4dfe55b7c0721877ebdc.js","a9a7754c-4dfe55b7c0721877ebdc.js.map","commons-2a628ef3c0ffddbbec42.js","commons-2a628ef3c0ffddbbec42.js.map","component---src-pages-30-minute-jams-js-adbf51cf96ae4bc4159c.js","component---src-pages-30-minute-jams-js-adbf51cf96ae4bc4159c.js.map"],"children":{},"childAssets":{}},"component---src-pages-404-js":{"chunks":[1,0,6],"assets":["a9a7754c-4dfe55b7c0721877ebdc.js","a9a7754c-4dfe55b7c0721877ebdc.js.map","commons-2a628ef3c0ffddbbec42.js","commons-2a628ef3c0ffddbbec42.js.map","component---src-pages-404-js-95aad802b084128f58cf.js","component---src-pages-404-js-95aad802b084128f58cf.js.map"],"children":{},"childAssets":{}},"component---src-pages-index-js":{"chunks":[1,4,0,7],"assets":["a9a7754c-4dfe55b7c0721877ebdc.js","a9a7754c-4dfe55b7c0721877ebdc.js.map","cb1608f2-d9331c34e752793a789a.js","cb1608f2-d9331c34e752793a789a.js.map","commons-2a628ef3c0ffddbbec42.js","commons-2a628ef3c0ffddbbec42.js.map","component---src-pages-index-js-be51e16c90b07d7399dc.js","component---src-pages-index-js-be51e16c90b07d7399dc.js.map"],"children":{},"childAssets":{}},"component---src-pages-music-js":{"chunks":[1,0,8],"assets":["a9a7754c-4dfe55b7c0721877ebdc.js","a9a7754c-4dfe55b7c0721877ebdc.js.map","commons-2a628ef3c0ffddbbec42.js","commons-2a628ef3c0ffddbbec42.js.map","component---src-pages-music-js-ecc183dada20b7f8b669.js","component---src-pages-music-js-ecc183dada20b7f8b669.js.map"],"children":{},"childAssets":{}},"component---src-pages-streams-js":{"chunks":[1,0,9],"assets":["a9a7754c-4dfe55b7c0721877ebdc.js","a9a7754c-4dfe55b7c0721877ebdc.js.map","commons-2a628ef3c0ffddbbec42.js","commons-2a628ef3c0ffddbbec42.js.map","component---src-pages-streams-js-d9bd60410c4171c73596.js","component---src-pages-streams-js-d9bd60410c4171c73596.js.map"],"children":{},"childAssets":{}},"component---src-pages-videos-js":{"chunks":[1,0,10],"assets":["a9a7754c-4dfe55b7c0721877ebdc.js","a9a7754c-4dfe55b7c0721877ebdc.js.map","commons-2a628ef3c0ffddbbec42.js","commons-2a628ef3c0ffddbbec42.js.map","component---src-pages-videos-js-75b5044afdccbdce5158.js","component---src-pages-videos-js-75b5044afdccbdce5158.js.map"],"children":{},"childAssets":{}}},"assetsByChunkName":{"polyfill":["webpack-runtime-980e121073cb30c1f4e4.js","commons-2a628ef3c0ffddbbec42.js","polyfill-8b52c04d9c14ad2efd64.js"],"app":["webpack-runtime-980e121073cb30c1f4e4.js","framework-85aff51d15c28c7fbe5f.js","styles.b439bc9f915495c62296.css","styles-5379f07abcd59a0e64bf.js","app-596f89afb85ee861135b.js"],"component---src-pages-30-minute-jams-js":["a9a7754c-4dfe55b7c0721877ebdc.js","commons-2a628ef3c0ffddbbec42.js","component---src-pages-30-minute-jams-js-adbf51cf96ae4bc4159c.js"],"component---src-pages-404-js":["a9a7754c-4dfe55b7c0721877ebdc.js","commons-2a628ef3c0ffddbbec42.js","component---src-pages-404-js-95aad802b084128f58cf.js"],"component---src-pages-index-js":["a9a7754c-4dfe55b7c0721877ebdc.js","cb1608f2-d9331c34e752793a789a.js","commons-2a628ef3c0ffddbbec42.js","component---src-pages-index-js-be51e16c90b07d7399dc.js"],"component---src-pages-music-js":["a9a7754c-4dfe55b7c0721877ebdc.js","commons-2a628ef3c0ffddbbec42.js","component---src-pages-music-js-ecc183dada20b7f8b669.js"],"component---src-pages-streams-js":["a9a7754c-4dfe55b7c0721877ebdc.js","commons-2a628ef3c0ffddbbec42.js","component---src-pages-streams-js-d9bd60410c4171c73596.js"],"component---src-pages-videos-js":["a9a7754c-4dfe55b7c0721877ebdc.js","commons-2a628ef3c0ffddbbec42.js","component---src-pages-videos-js-75b5044afdccbdce5158.js"]}}